{
  "protocol_version" : "0.0.6",
  "configuration" : {
    "version" : "(6.13.0) (explicit/1c8577ec)",
    "tlc" : "__thread",
    "sigsgev" : "normal",
    "notifications" : "kqueue",
    "architecture" : "arm64",
    "disabled_features" : "com,shared_perfcounters",
    "smallconfig" : "disabled",
    "bigarrays" : "disabled",
    "softdebug" : "enabled",
    "interpreter" : "enabled",
    "llvm_support" : "disabled",
    "suspend" : "preemptive"
  },
  "memory" : {
    "Resident Size" : "501596160",
    "Virtual Size" : "421949440000",
    "minor_gc_time" : "0",
    "major_gc_time" : "4244405",
    "minor_gc_count" : "0",
    "major_gc_count" : "30",
    "major_gc_time_concurrent" : "0"
 },
  "threads" : [
 {
    "is_managed" : true,
    "offset_free_hash" : "0xbc0ab8b8e",
    "offset_rich_hash" : "0xbc0ab8cc3",
    "crashed" : false,
    "native_thread_id" : "0x2b0207000",
    "thread_info_addr" : "0x160530400",
    "thread_name" : "WorkItemResultCountCache background saver",
    "ctx" : {
      "IP" : "0x18bd320ac",
      "SP" : "0x2b0206670",
      "BP" : "0x2b0206700"
  },
    "managed_frames" : [
  {
      "is_managed" : "false",
      "native_address" : "unregistered"
   }
,
  {
      "is_managed" : "true",
      "guid" : "E307BBB4-6710-4258-887A-104F6151F183",
      "token" : "0x00000",
      "native_offset" : "0x0",
      "filename" : "mscorlib.dll",
      "sizeofimage" : "0x470000",
      "timestamp" : "0xea247d52",
      "il_offset" : "0xffffffff"
   }
,
  {
      "is_managed" : "true",
      "guid" : "E307BBB4-6710-4258-887A-104F6151F183",
      "token" : "0x6001fa4",
      "native_offset" : "0x0",
      "filename" : "mscorlib.dll",
      "sizeofimage" : "0x470000",
      "timestamp" : "0xea247d52",
      "il_offset" : "0x00019"
   }
,
  {
      "is_managed" : "true",
      "guid" : "E86C2CA3-429E-4FB1-AE5E-6D944EB786FF",
      "token" : "0x6000198",
      "native_offset" : "0x0",
      "filename" : "Sirenix.OdinValidator.Editor.dll",
      "sizeofimage" : "0x7a000",
      "timestamp" : "0x653a7c5d",
      "il_offset" : "0x00000"
   }
,
  {
      "is_managed" : "true",
      "guid" : "E307BBB4-6710-4258-887A-104F6151F183",
      "token" : "0x6001f7d",
      "native_offset" : "0x0",
      "filename" : "mscorlib.dll",
      "sizeofimage" : "0x470000",
      "timestamp" : "0xea247d52",
      "il_offset" : "0x00014"
   }
,
  {
      "is_managed" : "true",
      "guid" : "E307BBB4-6710-4258-887A-104F6151F183",
      "token" : "0x6001f25",
      "native_offset" : "0x0",
      "filename" : "mscorlib.dll",
      "sizeofimage" : "0x470000",
      "timestamp" : "0xea247d52",
      "il_offset" : "0x00071"
   }
,
  {
      "is_managed" : "true",
      "guid" : "E307BBB4-6710-4258-887A-104F6151F183",
      "token" : "0x6001f23",
      "native_offset" : "0x0",
      "filename" : "mscorlib.dll",
      "sizeofimage" : "0x470000",
      "timestamp" : "0xea247d52",
      "il_offset" : "0x00000"
   }
,
  {
      "is_managed" : "true",
      "guid" : "E307BBB4-6710-4258-887A-104F6151F183",
      "token" : "0x6001f22",
      "native_offset" : "0x0",
      "filename" : "mscorlib.dll",
      "sizeofimage" : "0x470000",
      "timestamp" : "0xea247d52",
      "il_offset" : "0x0002b"
   }
,
  {
      "is_managed" : "true",
      "guid" : "E307BBB4-6710-4258-887A-104F6151F183",
      "token" : "0x6001f7f",
      "native_offset" : "0x0",
      "filename" : "mscorlib.dll",
      "sizeofimage" : "0x470000",
      "timestamp" : "0xea247d52",
      "il_offset" : "0x00008"
   }
,
  {
      "is_managed" : "true",
      "guid" : "E307BBB4-6710-4258-887A-104F6151F183",
      "token" : "0x00000",
      "native_offset" : "0x0",
      "filename" : "mscorlib.dll",
      "sizeofimage" : "0x470000",
      "timestamp" : "0xea247d52",
      "il_offset" : "0x00065"
   }

  ],
  "unmanaged_frames" : [
 {
    "is_managed" : "false",
    "native_address" : "0x1531051a0",
    "native_offset" : "0x00000"
  }
,
 {
    "is_managed" : "false",
    "native_address" : "0x15323c518",
    "native_offset" : "0x00000"
  }
,
 {
    "is_managed" : "false",
    "native_address" : "0x15323c874",
    "native_offset" : "0x00000"
  }
,
 {
    "is_managed" : "false",
    "native_address" : "0x15323c63c",
    "native_offset" : "0x00000"
  }
,
 {
    "is_managed" : "false",
    "native_address" : "0x1531463d0",
    "native_offset" : "0x00000"
  }
,
 {
    "is_managed" : "false",
    "native_address" : "0x18bd9da24",
    "native_offset" : "0x00000"
  }
,
 {
    "is_managed" : "false",
    "native_address" : "0x18bd6f628",
    "native_offset" : "0x00000"
  }
,
 {
    "is_managed" : "false",
    "native_address" : "0x15328bd6c",
    "native_offset" : "0x00000"
  }
,
 {
    "is_managed" : "false",
    "native_address" : "0x153295a48",
    "native_offset" : "0x00000"
  }
,
 {
    "is_managed" : "false",
    "native_address" : "0x153236628",
    "native_offset" : "0x00000"
  }
,
 {
    "is_managed" : "false",
    "native_address" : "0x1531e154c",
    "native_offset" : "0x00000"
  }
,
 {
    "is_managed" : "true",
    "guid" : "E307BBB4-6710-4258-887A-104F6151F183",
    "token" : "0x00000",
    "native_offset" : "0x0",
    "filename" : "mscorlib.dll",
    "sizeofimage" : "0x470000",
    "timestamp" : "0xea247d52",
    "il_offset" : "0x00000"
  }
,
 {
    "is_managed" : "true",
    "guid" : "E307BBB4-6710-4258-887A-104F6151F183",
    "token" : "0x6001fa4",
    "native_offset" : "0x0",
    "filename" : "mscorlib.dll",
    "sizeofimage" : "0x470000",
    "timestamp" : "0xea247d52",
    "il_offset" : "0x00000"
  }
,
 {
    "is_managed" : "true",
    "guid" : "E86C2CA3-429E-4FB1-AE5E-6D944EB786FF",
    "token" : "0x6000198",
    "native_offset" : "0x0",
    "filename" : "Sirenix.OdinValidator.Editor.dll",
    "sizeofimage" : "0x7a000",
    "timestamp" : "0x653a7c5d",
    "il_offset" : "0x00000"
  }
,
 {
    "is_managed" : "true",
    "guid" : "E307BBB4-6710-4258-887A-104F6151F183",
    "token" : "0x6001f7d",
    "native_offset" : "0x0",
    "filename" : "mscorlib.dll",
    "sizeofimage" : "0x470000",
    "timestamp" : "0xea247d52",
    "il_offset" : "0x00000"
  }
,
 {
    "is_managed" : "true",
    "guid" : "E307BBB4-6710-4258-887A-104F6151F183",
    "token" : "0x6001f25",
    "native_offset" : "0x0",
    "filename" : "mscorlib.dll",
    "sizeofimage" : "0x470000",
    "timestamp" : "0xea247d52",
    "il_offset" : "0x00000"
  }
,
 {
    "is_managed" : "true",
    "guid" : "E307BBB4-6710-4258-887A-104F6151F183",
    "token" : "0x6001f23",
    "native_offset" : "0x0",
    "filename" : "mscorlib.dll",
    "sizeofimage" : "0x470000",
    "timestamp" : "0xea247d52",
    "il_offset" : "0x00000"
  }
,
 {
    "is_managed" : "true",
    "guid" : "E307BBB4-6710-4258-887A-104F6151F183",
    "token" : "0x6001f22",
    "native_offset" : "0x0",
    "filename" : "mscorlib.dll",
    "sizeofimage" : "0x470000",
    "timestamp" : "0xea247d52",
    "il_offset" : "0x00000"
  }
,
 {
    "is_managed" : "true",
    "guid" : "E307BBB4-6710-4258-887A-104F6151F183",
    "token" : "0x6001f7f",
    "native_offset" : "0x0",
    "filename" : "mscorlib.dll",
    "sizeofimage" : "0x470000",
    "timestamp" : "0xea247d52",
    "il_offset" : "0x00000"
  }
,
 {
    "is_managed" : "true",
    "guid" : "E307BBB4-6710-4258-887A-104F6151F183",
    "token" : "0x00000",
    "native_offset" : "0x0",
    "filename" : "mscorlib.dll",
    "sizeofimage" : "0x470000",
    "timestamp" : "0xea247d52",
    "il_offset" : "0x00000"
  }
,
 {
    "is_managed" : "false",
    "native_address" : "0x153094d88",
    "native_offset" : "0x00000"
  }
,
 {
    "is_managed" : "false",
    "native_address" : "0x15321b24c",
    "native_offset" : "0x00000"
  }
,
 {
    "is_managed" : "false",
    "native_address" : "0x15321ce5c",
    "native_offset" : "0x00000"
  }
,
 {
    "is_managed" : "false",
    "native_address" : "0x15323d378",
    "native_offset" : "0x00000"
  }
,
 {
    "is_managed" : "false",
    "native_address" : "0x15323d130",
    "native_offset" : "0x00000"
  }
,
 {
    "is_managed" : "false",
    "native_address" : "0x1532bccf8",
    "native_offset" : "0x00000"
  }
,
 {
    "is_managed" : "false",
    "native_address" : "0x1532bcc80",
    "native_offset" : "0x00000"
  }
,
 {
    "is_managed" : "false",
    "native_address" : "0x18bd6f034",
    "native_offset" : "0x00000"
  }
,
 {
    "is_managed" : "false",
    "native_address" : "0x18bd69e3c",
    "native_offset" : "0x00000"
  }

 ]
},
{
  "is_managed" : false,
  "offset_free_hash" : "0x0",
  "offset_rich_hash" : "0x0",
  "crashed" : false,
  "native_thread_id" : "0x16c33b000",
  "thread_info_addr" : "0x1502aba00",
  "thread_name" : "tid_9403",
  "ctx" : {
    "IP" : "0x18bd2e830",
    "SP" : "0x16c33ad10",
    "BP" : "0x16c33ad20"
 },
  "unmanaged_frames" : [
 {
    "is_managed" : "false",
    "native_address" : "0x1531051a0",
    "native_offset" : "0x00000"
  }
,
 {
    "is_managed" : "false",
    "native_address" : "0x15323c518",
    "native_offset" : "0x00000"
  }
,
 {
    "is_managed" : "false",
    "native_address" : "0x15323c874",
    "native_offset" : "0x00000"
  }
,
 {
    "is_managed" : "false",
    "native_address" : "0x15323c63c",
    "native_offset" : "0x00000"
  }
,
 {
    "is_managed" : "false",
    "native_address" : "0x1531463d0",
    "native_offset" : "0x00000"
  }
,
 {
    "is_managed" : "false",
    "native_address" : "0x18bd9da24",
    "native_offset" : "0x00000"
  }
,
 {
    "is_managed" : "false",
    "native_address" : "0x18bbc1eac",
    "native_offset" : "0x00000"
  }
,
 {
    "is_managed" : "false",
    "native_address" : "0x18bbc255c",
    "native_offset" : "0x00000"
  }
,
 {
    "is_managed" : "false",
    "native_address" : "0x106f0ec64",
    "native_offset" : "0x00000"
  }
,
 {
    "is_managed" : "false",
    "native_address" : "0x104beb6ec",
    "native_offset" : "0x00000"
  }
,
 {
    "is_managed" : "false",
    "native_address" : "0x104bec9cc",
    "native_offset" : "0x00000"
  }
,
 {
    "is_managed" : "false",
    "native_address" : "0x104e51b20",
    "native_offset" : "0x00000"
  }
,
 {
    "is_managed" : "false",
    "native_address" : "0x18bd6f034",
    "native_offset" : "0x00000"
  }
,
 {
    "is_managed" : "false",
    "native_address" : "0x18bd69e3c",
    "native_offset" : "0x00000"
  }

 ]
},
{
  "is_managed" : false,
  "offset_free_hash" : "0x0",
  "offset_rich_hash" : "0x0",
  "crashed" : true,
  "native_thread_id" : "0x1e3035300",
  "thread_info_addr" : "0x151036000",
  "thread_name" : "tid_103",
  "ctx" : {
    "IP" : "0x104da942c",
    "SP" : "0x16bb08b90",
    "BP" : "0x16bb08ba0"
 },
  "unmanaged_frames" : [
 {
    "is_managed" : "false",
    "native_address" : "0x1531051a0",
    "native_offset" : "0x00000"
  }
,
 {
    "is_managed" : "false",
    "native_address" : "0x15323c518",
    "native_offset" : "0x00000"
  }
,
 {
    "is_managed" : "false",
    "native_address" : "0x15323c874",
    "native_offset" : "0x00000"
  }
,
 {
    "is_managed" : "false",
    "native_address" : "0x15323ce64",
    "native_offset" : "0x00000"
  }
,
 {
    "is_managed" : "false",
    "native_address" : "0x15314721c",
    "native_offset" : "0x00000"
  }
,
 {
    "is_managed" : "false",
    "native_address" : "0x153109338",
    "native_offset" : "0x00000"
  }
,
 {
    "is_managed" : "false",
    "native_address" : "0x153091ac8",
    "native_offset" : "0x00000"
  }
,
 {
    "is_managed" : "false",
    "native_address" : "0x18bd9da24",
    "native_offset" : "0x00000"
  }
,
 {
    "is_managed" : "false",
    "native_address" : "0x104da9418",
    "native_offset" : "0x00000"
  }
,
 {
    "is_managed" : "false",
    "native_address" : "0x104da5d58",
    "native_offset" : "0x00000"
  }
,
 {
    "is_managed" : "false",
    "native_address" : "0x104daba20",
    "native_offset" : "0x00000"
  }
,
 {
    "is_managed" : "false",
    "native_address" : "0x104d773b8",
    "native_offset" : "0x00000"
  }
,
 {
    "is_managed" : "false",
    "native_address" : "0x104d7b098",
    "native_offset" : "0x00000"
  }
,
 {
    "is_managed" : "false",
    "native_address" : "0x1067cc454",
    "native_offset" : "0x00000"
  }
,
 {
    "is_managed" : "false",
    "native_address" : "0x1067cc724",
    "native_offset" : "0x00000"
  }
,
 {
    "is_managed" : "false",
    "native_address" : "0x105101ac0",
    "native_offset" : "0x00000"
  }
,
 {
    "is_managed" : "false",
    "native_address" : "0x1051017cc",
    "native_offset" : "0x00000"
  }
,
 {
    "is_managed" : "false",
    "native_address" : "0x105101508",
    "native_offset" : "0x00000"
  }
,
 {
    "is_managed" : "false",
    "native_address" : "0x1050d4eac",
    "native_offset" : "0x00000"
  }
,
 {
    "is_managed" : "false",
    "native_address" : "0x1050d5d90",
    "native_offset" : "0x00000"
  }
,
 {
    "is_managed" : "false",
    "native_address" : "0x1050d7e10",
    "native_offset" : "0x00000"
  }
,
 {
    "is_managed" : "false",
    "native_address" : "0x106445944",
    "native_offset" : "0x00000"
  }
,
 {
    "is_managed" : "false",
    "native_address" : "0x106447a3c",
    "native_offset" : "0x00000"
  }
,
 {
    "is_managed" : "false",
    "native_address" : "0x10640b854",
    "native_offset" : "0x00000"
  }
,
 {
    "is_managed" : "false",
    "native_address" : "0x18bbc1910",
    "native_offset" : "0x00000"
  }
,
 {
    "is_managed" : "false",
    "native_address" : "0x18bbd0d9c",
    "native_offset" : "0x00000"
  }
,
 {
    "is_managed" : "false",
    "native_address" : "0x18bbc1910",
    "native_offset" : "0x00000"
  }
,
 {
    "is_managed" : "false",
    "native_address" : "0x18bbcffa8",
    "native_offset" : "0x00000"
  }
,
 {
    "is_managed" : "false",
    "native_address" : "0x18bbcfbc0",
    "native_offset" : "0x00000"
  }
,
 {
    "is_managed" : "false",
    "native_address" : "0x18be8d220",
    "native_offset" : "0x00000"
  }
,
 {
    "is_managed" : "false",
    "native_address" : "0x18be4aaac",
    "native_offset" : "0x00000"
  }
,
 {
    "is_managed" : "false",
    "native_address" : "0x18be49c2c",
    "native_offset" : "0x00000"
  }
,
 {
    "is_managed" : "false",
    "native_address" : "0x1963a2448",
    "native_offset" : "0x00000"
  }
,
 {
    "is_managed" : "false",
    "native_address" : "0x1963a2284",
    "native_offset" : "0x00000"
  }
,
 {
    "is_managed" : "false",
    "native_address" : "0x1963a1fdc",
    "native_offset" : "0x00000"
  }
,
 {
    "is_managed" : "false",
    "native_address" : "0x18f624f90",
    "native_offset" : "0x00000"
  }
,
 {
    "is_managed" : "false",
    "native_address" : "0x18fdf8b94",
    "native_offset" : "0x00000"
  }
,
 {
    "is_managed" : "false",
    "native_address" : "0x18f61843c",
    "native_offset" : "0x00000"
  }
,
 {
    "is_managed" : "false",
    "native_address" : "0x18f5ef708",
    "native_offset" : "0x00000"
  }
,
 {
    "is_managed" : "false",
    "native_address" : "0x106e65ab4",
    "native_offset" : "0x00000"
  }
,
 {
    "is_managed" : "false",
    "native_address" : "0x106e65e00",
    "native_offset" : "0x00000"
  }
,
 {
    "is_managed" : "false",
    "native_address" : "0x18b9f5058",
    "native_offset" : "0x00000"
  }

 ]
},
{
  "is_managed" : false,
  "offset_free_hash" : "0x0",
  "offset_rich_hash" : "0x0",
  "crashed" : false,
  "native_thread_id" : "0x16f4c7000",
  "thread_info_addr" : "0x2c6f85200",
  "thread_name" : "tid_3e12f",
  "ctx" : {
    "IP" : "0x18bd2e830",
    "SP" : "0x16f4c6d90",
    "BP" : "0x16f4c6da0"
 },
  "unmanaged_frames" : [
 {
    "is_managed" : "false",
    "native_address" : "0x1531051a0",
    "native_offset" : "0x00000"
  }
,
 {
    "is_managed" : "false",
    "native_address" : "0x15323c518",
    "native_offset" : "0x00000"
  }
,
 {
    "is_managed" : "false",
    "native_address" : "0x15323c874",
    "native_offset" : "0x00000"
  }
,
 {
    "is_managed" : "false",
    "native_address" : "0x15323c63c",
    "native_offset" : "0x00000"
  }
,
 {
    "is_managed" : "false",
    "native_address" : "0x1531463d0",
    "native_offset" : "0x00000"
  }
,
 {
    "is_managed" : "false",
    "native_address" : "0x18bd9da24",
    "native_offset" : "0x00000"
  }
,
 {
    "is_managed" : "false",
    "native_address" : "0x18bbc1eac",
    "native_offset" : "0x00000"
  }
,
 {
    "is_managed" : "false",
    "native_address" : "0x18bbc255c",
    "native_offset" : "0x00000"
  }
,
 {
    "is_managed" : "false",
    "native_address" : "0x106f0ec64",
    "native_offset" : "0x00000"
  }
,
 {
    "is_managed" : "false",
    "native_address" : "0x10489b6fc",
    "native_offset" : "0x00000"
  }
,
 {
    "is_managed" : "false",
    "native_address" : "0x104ca0174",
    "native_offset" : "0x00000"
  }
,
 {
    "is_managed" : "false",
    "native_address" : "0x104ca0110",
    "native_offset" : "0x00000"
  }
,
 {
    "is_managed" : "false",
    "native_address" : "0x104e51b20",
    "native_offset" : "0x00000"
  }
,
 {
    "is_managed" : "false",
    "native_address" : "0x18bd6f034",
    "native_offset" : "0x00000"
  }
,
 {
    "is_managed" : "false",
    "native_address" : "0x18bd69e3c",
    "native_offset" : "0x00000"
  }

 ]
},
{
  "is_managed" : false,
  "offset_free_hash" : "0x0",
  "offset_rich_hash" : "0x0",
  "crashed" : false,
  "native_thread_id" : "0x16dbff000",
  "thread_info_addr" : "0x15205c600",
  "thread_name" : "Finalizer",
  "ctx" : {
    "IP" : "0x18bd2e830",
    "SP" : "0x16dbfedd0",
    "BP" : "0x16dbfee50"
 },
  "unmanaged_frames" : [
 {
    "is_managed" : "false",
    "native_address" : "0x1531051a0",
    "native_offset" : "0x00000"
  }
,
 {
    "is_managed" : "false",
    "native_address" : "0x15323c518",
    "native_offset" : "0x00000"
  }
,
 {
    "is_managed" : "false",
    "native_address" : "0x15323c874",
    "native_offset" : "0x00000"
  }
,
 {
    "is_managed" : "false",
    "native_address" : "0x15323c63c",
    "native_offset" : "0x00000"
  }
,
 {
    "is_managed" : "false",
    "native_address" : "0x1531463d0",
    "native_offset" : "0x00000"
  }
,
 {
    "is_managed" : "false",
    "native_address" : "0x18bd9da24",
    "native_offset" : "0x00000"
  }
,
 {
    "is_managed" : "false",
    "native_address" : "0x15327616c",
    "native_offset" : "0x00000"
  }
,
 {
    "is_managed" : "false",
    "native_address" : "0x15323d284",
    "native_offset" : "0x00000"
  }
,
 {
    "is_managed" : "false",
    "native_address" : "0x15323d130",
    "native_offset" : "0x00000"
  }
,
 {
    "is_managed" : "false",
    "native_address" : "0x1532bccf8",
    "native_offset" : "0x00000"
  }
,
 {
    "is_managed" : "false",
    "native_address" : "0x1532bcc80",
    "native_offset" : "0x00000"
  }
,
 {
    "is_managed" : "false",
    "native_address" : "0x18bd6f034",
    "native_offset" : "0x00000"
  }
,
 {
    "is_managed" : "false",
    "native_address" : "0x18bd69e3c",
    "native_offset" : "0x00000"
  }

 ]
},
{
  "is_managed" : true,
  "offset_free_hash" : "0xbec64873c",
  "offset_rich_hash" : "0xbec648877",
  "crashed" : false,
  "native_thread_id" : "0x2b0413000",
  "thread_info_addr" : "0x2c7d4ca00",
  "thread_name" : "Expression Cache Cleanup Thread",
  "ctx" : {
    "IP" : "0x18bd320ac",
    "SP" : "0x2b0412330",
    "BP" : "0x2b04123c0"
 },
  "managed_frames" : [
 {
    "is_managed" : "false",
    "native_address" : "unregistered"
  }
,
 {
    "is_managed" : "true",
    "guid" : "E307BBB4-6710-4258-887A-104F6151F183",
    "token" : "0x00000",
    "native_offset" : "0x0",
    "filename" : "mscorlib.dll",
    "sizeofimage" : "0x470000",
    "timestamp" : "0xea247d52",
    "il_offset" : "0xffffffff"
  }
,
 {
    "is_managed" : "true",
    "guid" : "E307BBB4-6710-4258-887A-104F6151F183",
    "token" : "0x6001fa4",
    "native_offset" : "0x0",
    "filename" : "mscorlib.dll",
    "sizeofimage" : "0x470000",
    "timestamp" : "0xea247d52",
    "il_offset" : "0x00019"
  }
,
 {
    "is_managed" : "true",
    "guid" : "86EBD068-E0AD-4376-95A6-9D341F7F793B",
    "token" : "0x6000701",
    "native_offset" : "0x0",
    "filename" : "Sirenix.Utilities.Editor.dll",
    "sizeofimage" : "0x12e000",
    "timestamp" : "0x653a7c04",
    "il_offset" : "0x00006"
  }
,
 {
    "is_managed" : "true",
    "guid" : "E307BBB4-6710-4258-887A-104F6151F183",
    "token" : "0x6001f7d",
    "native_offset" : "0x0",
    "filename" : "mscorlib.dll",
    "sizeofimage" : "0x470000",
    "timestamp" : "0xea247d52",
    "il_offset" : "0x00014"
  }
,
 {
    "is_managed" : "true",
    "guid" : "E307BBB4-6710-4258-887A-104F6151F183",
    "token" : "0x6001f25",
    "native_offset" : "0x0",
    "filename" : "mscorlib.dll",
    "sizeofimage" : "0x470000",
    "timestamp" : "0xea247d52",
    "il_offset" : "0x00071"
  }
,
 {
    "is_managed" : "true",
    "guid" : "E307BBB4-6710-4258-887A-104F6151F183",
    "token" : "0x6001f23",
    "native_offset" : "0x0",
    "filename" : "mscorlib.dll",
    "sizeofimage" : "0x470000",
    "timestamp" : "0xea247d52",
    "il_offset" : "0x00000"
  }
,
 {
    "is_managed" : "true",
    "guid" : "E307BBB4-6710-4258-887A-104F6151F183",
    "token" : "0x6001f22",
    "native_offset" : "0x0",
    "filename" : "mscorlib.dll",
    "sizeofimage" : "0x470000",
    "timestamp" : "0xea247d52",
    "il_offset" : "0x0002b"
  }
,
 {
    "is_managed" : "true",
    "guid" : "E307BBB4-6710-4258-887A-104F6151F183",
    "token" : "0x6001f7f",
    "native_offset" : "0x0",
    "filename" : "mscorlib.dll",
    "sizeofimage" : "0x470000",
    "timestamp" : "0xea247d52",
    "il_offset" : "0x00008"
  }
,
 {
    "is_managed" : "true",
    "guid" : "E307BBB4-6710-4258-887A-104F6151F183",
    "token" : "0x00000",
    "native_offset" : "0x0",
    "filename" : "mscorlib.dll",
    "sizeofimage" : "0x470000",
    "timestamp" : "0xea247d52",
    "il_offset" : "0x00065"
  }

 ],
"unmanaged_frames" : [
{
  "is_managed" : "false",
  "native_address" : "0x1531051a0",
  "native_offset" : "0x00000"
 }
,
{
  "is_managed" : "false",
  "native_address" : "0x15323c518",
  "native_offset" : "0x00000"
 }
,
{
  "is_managed" : "false",
  "native_address" : "0x15323c874",
  "native_offset" : "0x00000"
 }
,
{
  "is_managed" : "false",
  "native_address" : "0x15323c63c",
  "native_offset" : "0x00000"
 }
,
{
  "is_managed" : "false",
  "native_address" : "0x1531463d0",
  "native_offset" : "0x00000"
 }
,
{
  "is_managed" : "false",
  "native_address" : "0x18bd9da24",
  "native_offset" : "0x00000"
 }
,
{
  "is_managed" : "false",
  "native_address" : "0x18bd6f628",
  "native_offset" : "0x00000"
 }
,
{
  "is_managed" : "false",
  "native_address" : "0x15328bd6c",
  "native_offset" : "0x00000"
 }
,
{
  "is_managed" : "false",
  "native_address" : "0x153295a48",
  "native_offset" : "0x00000"
 }
,
{
  "is_managed" : "false",
  "native_address" : "0x153236628",
  "native_offset" : "0x00000"
 }
,
{
  "is_managed" : "false",
  "native_address" : "0x1531e154c",
  "native_offset" : "0x00000"
 }
,
{
  "is_managed" : "true",
  "guid" : "E307BBB4-6710-4258-887A-104F6151F183",
  "token" : "0x00000",
  "native_offset" : "0x0",
  "filename" : "mscorlib.dll",
  "sizeofimage" : "0x470000",
  "timestamp" : "0xea247d52",
  "il_offset" : "0x00000"
 }
,
{
  "is_managed" : "true",
  "guid" : "E307BBB4-6710-4258-887A-104F6151F183",
  "token" : "0x6001fa4",
  "native_offset" : "0x0",
  "filename" : "mscorlib.dll",
  "sizeofimage" : "0x470000",
  "timestamp" : "0xea247d52",
  "il_offset" : "0x00000"
 }
,
{
  "is_managed" : "true",
  "guid" : "86EBD068-E0AD-4376-95A6-9D341F7F793B",
  "token" : "0x6000701",
  "native_offset" : "0x0",
  "filename" : "Sirenix.Utilities.Editor.dll",
  "sizeofimage" : "0x12e000",
  "timestamp" : "0x653a7c04",
  "il_offset" : "0x00000"
 }
,
{
  "is_managed" : "true",
  "guid" : "E307BBB4-6710-4258-887A-104F6151F183",
  "token" : "0x6001f7d",
  "native_offset" : "0x0",
  "filename" : "mscorlib.dll",
  "sizeofimage" : "0x470000",
  "timestamp" : "0xea247d52",
  "il_offset" : "0x00000"
 }
,
{
  "is_managed" : "true",
  "guid" : "E307BBB4-6710-4258-887A-104F6151F183",
  "token" : "0x6001f25",
  "native_offset" : "0x0",
  "filename" : "mscorlib.dll",
  "sizeofimage" : "0x470000",
  "timestamp" : "0xea247d52",
  "il_offset" : "0x00000"
 }
,
{
  "is_managed" : "true",
  "guid" : "E307BBB4-6710-4258-887A-104F6151F183",
  "token" : "0x6001f23",
  "native_offset" : "0x0",
  "filename" : "mscorlib.dll",
  "sizeofimage" : "0x470000",
  "timestamp" : "0xea247d52",
  "il_offset" : "0x00000"
 }
,
{
  "is_managed" : "true",
  "guid" : "E307BBB4-6710-4258-887A-104F6151F183",
  "token" : "0x6001f22",
  "native_offset" : "0x0",
  "filename" : "mscorlib.dll",
  "sizeofimage" : "0x470000",
  "timestamp" : "0xea247d52",
  "il_offset" : "0x00000"
 }
,
{
  "is_managed" : "true",
  "guid" : "E307BBB4-6710-4258-887A-104F6151F183",
  "token" : "0x6001f7f",
  "native_offset" : "0x0",
  "filename" : "mscorlib.dll",
  "sizeofimage" : "0x470000",
  "timestamp" : "0xea247d52",
  "il_offset" : "0x00000"
 }
,
{
  "is_managed" : "true",
  "guid" : "E307BBB4-6710-4258-887A-104F6151F183",
  "token" : "0x00000",
  "native_offset" : "0x0",
  "filename" : "mscorlib.dll",
  "sizeofimage" : "0x470000",
  "timestamp" : "0xea247d52",
  "il_offset" : "0x00000"
 }
,
{
  "is_managed" : "false",
  "native_address" : "0x153094d88",
  "native_offset" : "0x00000"
 }
,
{
  "is_managed" : "false",
  "native_address" : "0x15321b24c",
  "native_offset" : "0x00000"
 }
,
{
  "is_managed" : "false",
  "native_address" : "0x15321ce5c",
  "native_offset" : "0x00000"
 }
,
{
  "is_managed" : "false",
  "native_address" : "0x15323d378",
  "native_offset" : "0x00000"
 }
,
{
  "is_managed" : "false",
  "native_address" : "0x15323d130",
  "native_offset" : "0x00000"
 }
,
{
  "is_managed" : "false",
  "native_address" : "0x1532bccf8",
  "native_offset" : "0x00000"
 }
,
{
  "is_managed" : "false",
  "native_address" : "0x1532bcc80",
  "native_offset" : "0x00000"
 }
,
{
  "is_managed" : "false",
  "native_address" : "0x18bd6f034",
  "native_offset" : "0x00000"
 }
,
{
  "is_managed" : "false",
  "native_address" : "0x18bd69e3c",
  "native_offset" : "0x00000"
 }

]
},
{
"is_managed" : true,
"offset_free_hash" : "0x1224727402",
"offset_rich_hash" : "0x12247275cb",
"crashed" : false,
"native_thread_id" : "0x16fc47000",
"thread_info_addr" : "0x160575800",
"thread_name" : "Timer-Scheduler",
"ctx" : {
  "IP" : "0x18bd320ac",
  "SP" : "0x16fc45ec0",
  "BP" : "0x16fc45f50"
},
"managed_frames" : [
{
  "is_managed" : "false",
  "native_address" : "unregistered"
 }
,
{
  "is_managed" : "true",
  "guid" : "E307BBB4-6710-4258-887A-104F6151F183",
  "token" : "0x00000",
  "native_offset" : "0x0",
  "filename" : "mscorlib.dll",
  "sizeofimage" : "0x470000",
  "timestamp" : "0xea247d52",
  "il_offset" : "0xffffffff"
 }
,
{
  "is_managed" : "true",
  "guid" : "E307BBB4-6710-4258-887A-104F6151F183",
  "token" : "0x60020b2",
  "native_offset" : "0x0",
  "filename" : "mscorlib.dll",
  "sizeofimage" : "0x470000",
  "timestamp" : "0xea247d52",
  "il_offset" : "0x00044"
 }
,
{
  "is_managed" : "true",
  "guid" : "E307BBB4-6710-4258-887A-104F6151F183",
  "token" : "0x600209e",
  "native_offset" : "0x0",
  "filename" : "mscorlib.dll",
  "sizeofimage" : "0x470000",
  "timestamp" : "0xea247d52",
  "il_offset" : "0x00014"
 }
,
{
  "is_managed" : "true",
  "guid" : "E307BBB4-6710-4258-887A-104F6151F183",
  "token" : "0x600209d",
  "native_offset" : "0x0",
  "filename" : "mscorlib.dll",
  "sizeofimage" : "0x470000",
  "timestamp" : "0xea247d52",
  "il_offset" : "0x00000"
 }
,
{
  "is_managed" : "true",
  "guid" : "E307BBB4-6710-4258-887A-104F6151F183",
  "token" : "0x6002098",
  "native_offset" : "0x0",
  "filename" : "mscorlib.dll",
  "sizeofimage" : "0x470000",
  "timestamp" : "0xea247d52",
  "il_offset" : "0x00019"
 }
,
{
  "is_managed" : "true",
  "guid" : "E307BBB4-6710-4258-887A-104F6151F183",
  "token" : "0x600209b",
  "native_offset" : "0x0",
  "filename" : "mscorlib.dll",
  "sizeofimage" : "0x470000",
  "timestamp" : "0xea247d52",
  "il_offset" : "0x00000"
 }
,
{
  "is_managed" : "true",
  "guid" : "E307BBB4-6710-4258-887A-104F6151F183",
  "token" : "0x600215a",
  "native_offset" : "0x0",
  "filename" : "mscorlib.dll",
  "sizeofimage" : "0x470000",
  "timestamp" : "0xea247d52",
  "il_offset" : "0x0003c"
 }
,
{
  "is_managed" : "true",
  "guid" : "E307BBB4-6710-4258-887A-104F6151F183",
  "token" : "0x6001f7d",
  "native_offset" : "0x0",
  "filename" : "mscorlib.dll",
  "sizeofimage" : "0x470000",
  "timestamp" : "0xea247d52",
  "il_offset" : "0x00014"
 }
,
{
  "is_managed" : "true",
  "guid" : "E307BBB4-6710-4258-887A-104F6151F183",
  "token" : "0x6001f25",
  "native_offset" : "0x0",
  "filename" : "mscorlib.dll",
  "sizeofimage" : "0x470000",
  "timestamp" : "0xea247d52",
  "il_offset" : "0x00071"
 }
,
{
  "is_managed" : "true",
  "guid" : "E307BBB4-6710-4258-887A-104F6151F183",
  "token" : "0x6001f23",
  "native_offset" : "0x0",
  "filename" : "mscorlib.dll",
  "sizeofimage" : "0x470000",
  "timestamp" : "0xea247d52",
  "il_offset" : "0x00000"
 }
,
{
  "is_managed" : "true",
  "guid" : "E307BBB4-6710-4258-887A-104F6151F183",
  "token" : "0x6001f22",
  "native_offset" : "0x0",
  "filename" : "mscorlib.dll",
  "sizeofimage" : "0x470000",
  "timestamp" : "0xea247d52",
  "il_offset" : "0x0002b"
 }
,
{
  "is_managed" : "true",
  "guid" : "E307BBB4-6710-4258-887A-104F6151F183",
  "token" : "0x6001f7f",
  "native_offset" : "0x0",
  "filename" : "mscorlib.dll",
  "sizeofimage" : "0x470000",
  "timestamp" : "0xea247d52",
  "il_offset" : "0x00008"
 }
,
{
  "is_managed" : "true",
  "guid" : "E307BBB4-6710-4258-887A-104F6151F183",
  "token" : "0x00000",
  "native_offset" : "0x0",
  "filename" : "mscorlib.dll",
  "sizeofimage" : "0x470000",
  "timestamp" : "0xea247d52",
  "il_offset" : "0x00065"
 }

],
"unmanaged_frames" : [
{
"is_managed" : "false",
"native_address" : "0x1531051a0",
"native_offset" : "0x00000"
}
,
{
"is_managed" : "false",
"native_address" : "0x15323c518",
"native_offset" : "0x00000"
}
,
{
"is_managed" : "false",
"native_address" : "0x15323c874",
"native_offset" : "0x00000"
}
,
{
"is_managed" : "false",
"native_address" : "0x15323c63c",
"native_offset" : "0x00000"
}
,
{
"is_managed" : "false",
"native_address" : "0x1531463d0",
"native_offset" : "0x00000"
}
,
{
"is_managed" : "false",
"native_address" : "0x18bd9da24",
"native_offset" : "0x00000"
}
,
{
"is_managed" : "false",
"native_address" : "0x18bd6f628",
"native_offset" : "0x00000"
}
,
{
"is_managed" : "false",
"native_address" : "0x15328bd6c",
"native_offset" : "0x00000"
}
,
{
"is_managed" : "false",
"native_address" : "0x153248248",
"native_offset" : "0x00000"
}
,
{
"is_managed" : "false",
"native_address" : "0x15324807c",
"native_offset" : "0x00000"
}
,
{
"is_managed" : "false",
"native_address" : "0x153248314",
"native_offset" : "0x00000"
}
,
{
"is_managed" : "false",
"native_address" : "0x1532376e8",
"native_offset" : "0x00000"
}
,
{
"is_managed" : "false",
"native_address" : "0x1531e1e2c",
"native_offset" : "0x00000"
}
,
{
"is_managed" : "true",
"guid" : "E307BBB4-6710-4258-887A-104F6151F183",
"token" : "0x00000",
"native_offset" : "0x0",
"filename" : "mscorlib.dll",
"sizeofimage" : "0x470000",
"timestamp" : "0xea247d52",
"il_offset" : "0x00000"
}
,
{
"is_managed" : "true",
"guid" : "E307BBB4-6710-4258-887A-104F6151F183",
"token" : "0x60020b2",
"native_offset" : "0x0",
"filename" : "mscorlib.dll",
"sizeofimage" : "0x470000",
"timestamp" : "0xea247d52",
"il_offset" : "0x00000"
}
,
{
"is_managed" : "true",
"guid" : "E307BBB4-6710-4258-887A-104F6151F183",
"token" : "0x600209e",
"native_offset" : "0x0",
"filename" : "mscorlib.dll",
"sizeofimage" : "0x470000",
"timestamp" : "0xea247d52",
"il_offset" : "0x00000"
}
,
{
"is_managed" : "true",
"guid" : "E307BBB4-6710-4258-887A-104F6151F183",
"token" : "0x600209d",
"native_offset" : "0x0",
"filename" : "mscorlib.dll",
"sizeofimage" : "0x470000",
"timestamp" : "0xea247d52",
"il_offset" : "0x00000"
}
,
{
"is_managed" : "true",
"guid" : "E307BBB4-6710-4258-887A-104F6151F183",
"token" : "0x6002098",
"native_offset" : "0x0",
"filename" : "mscorlib.dll",
"sizeofimage" : "0x470000",
"timestamp" : "0xea247d52",
"il_offset" : "0x00000"
}
,
{
"is_managed" : "true",
"guid" : "E307BBB4-6710-4258-887A-104F6151F183",
"token" : "0x600209b",
"native_offset" : "0x0",
"filename" : "mscorlib.dll",
"sizeofimage" : "0x470000",
"timestamp" : "0xea247d52",
"il_offset" : "0x00000"
}
,
{
"is_managed" : "true",
"guid" : "E307BBB4-6710-4258-887A-104F6151F183",
"token" : "0x600215a",
"native_offset" : "0x0",
"filename" : "mscorlib.dll",
"sizeofimage" : "0x470000",
"timestamp" : "0xea247d52",
"il_offset" : "0x00000"
}
,
{
"is_managed" : "true",
"guid" : "E307BBB4-6710-4258-887A-104F6151F183",
"token" : "0x6001f7d",
"native_offset" : "0x0",
"filename" : "mscorlib.dll",
"sizeofimage" : "0x470000",
"timestamp" : "0xea247d52",
"il_offset" : "0x00000"
}
,
{
"is_managed" : "true",
"guid" : "E307BBB4-6710-4258-887A-104F6151F183",
"token" : "0x6001f25",
"native_offset" : "0x0",
"filename" : "mscorlib.dll",
"sizeofimage" : "0x470000",
"timestamp" : "0xea247d52",
"il_offset" : "0x00000"
}
,
{
"is_managed" : "true",
"guid" : "E307BBB4-6710-4258-887A-104F6151F183",
"token" : "0x6001f23",
"native_offset" : "0x0",
"filename" : "mscorlib.dll",
"sizeofimage" : "0x470000",
"timestamp" : "0xea247d52",
"il_offset" : "0x00000"
}
,
{
"is_managed" : "true",
"guid" : "E307BBB4-6710-4258-887A-104F6151F183",
"token" : "0x6001f22",
"native_offset" : "0x0",
"filename" : "mscorlib.dll",
"sizeofimage" : "0x470000",
"timestamp" : "0xea247d52",
"il_offset" : "0x00000"
}
,
{
"is_managed" : "true",
"guid" : "E307BBB4-6710-4258-887A-104F6151F183",
"token" : "0x6001f7f",
"native_offset" : "0x0",
"filename" : "mscorlib.dll",
"sizeofimage" : "0x470000",
"timestamp" : "0xea247d52",
"il_offset" : "0x00000"
}
,
{
"is_managed" : "true",
"guid" : "E307BBB4-6710-4258-887A-104F6151F183",
"token" : "0x00000",
"native_offset" : "0x0",
"filename" : "mscorlib.dll",
"sizeofimage" : "0x470000",
"timestamp" : "0xea247d52",
"il_offset" : "0x00000"
}
,
{
"is_managed" : "false",
"native_address" : "0x153094d88",
"native_offset" : "0x00000"
}
,
{
"is_managed" : "false",
"native_address" : "0x15321b24c",
"native_offset" : "0x00000"
}
,
{
"is_managed" : "false",
"native_address" : "0x15321ce5c",
"native_offset" : "0x00000"
}
,
{
"is_managed" : "false",
"native_address" : "0x15323d378",
"native_offset" : "0x00000"
}
,
{
"is_managed" : "false",
"native_address" : "0x15323d130",
"native_offset" : "0x00000"
}
,
{
"is_managed" : "false",
"native_address" : "0x1532bccf8",
"native_offset" : "0x00000"
}
,
{
"is_managed" : "false",
"native_address" : "0x1532bcc80",
"native_offset" : "0x00000"
}
,
{
"is_managed" : "false",
"native_address" : "0x18bd6f034",
"native_offset" : "0x00000"
}
,
{
"is_managed" : "false",
"native_address" : "0x18bd69e3c",
"native_offset" : "0x00000"
}

]
},
{
"is_managed" : false,
"offset_free_hash" : "0x0",
"offset_rich_hash" : "0x0",
"crashed" : false,
"native_thread_id" : "0x16de0b000",
"thread_info_addr" : "0x1510e6200",
"thread_name" : "Debugger agent",
"ctx" : {
"IP" : "0x18bd37200",
"SP" : "0x16de0aaa0",
"BP" : "0x16de0aae0"
},
"unmanaged_frames" : [
{
"is_managed" : "false",
"native_address" : "0x1531051a0",
"native_offset" : "0x00000"
}
,
{
"is_managed" : "false",
"native_address" : "0x15323c518",
"native_offset" : "0x00000"
}
,
{
"is_managed" : "false",
"native_address" : "0x15323c874",
"native_offset" : "0x00000"
}
,
{
"is_managed" : "false",
"native_address" : "0x15323c63c",
"native_offset" : "0x00000"
}
,
{
"is_managed" : "false",
"native_address" : "0x1531463d0",
"native_offset" : "0x00000"
}
,
{
"is_managed" : "false",
"native_address" : "0x18bd9da24",
"native_offset" : "0x00000"
}
,
{
"is_managed" : "false",
"native_address" : "0x15317559c",
"native_offset" : "0x00000"
}
,
{
"is_managed" : "false",
"native_address" : "0x15316c198",
"native_offset" : "0x00000"
}
,
{
"is_managed" : "false",
"native_address" : "0x15323d284",
"native_offset" : "0x00000"
}
,
{
"is_managed" : "false",
"native_address" : "0x15323d130",
"native_offset" : "0x00000"
}
,
{
"is_managed" : "false",
"native_address" : "0x1532bccf8",
"native_offset" : "0x00000"
}
,
{
"is_managed" : "false",
"native_address" : "0x1532bcc80",
"native_offset" : "0x00000"
}
,
{
"is_managed" : "false",
"native_address" : "0x18bd6f034",
"native_offset" : "0x00000"
}
,
{
"is_managed" : "false",
"native_address" : "0x18bd69e3c",
"native_offset" : "0x00000"
}

]
}
]
}